LICENSE
MANIFEST.in
README.md
pyproject.toml
setup.py
dwtools3/__init__.py
dwtools3.egg-info/PKG-INFO
dwtools3.egg-info/SOURCES.txt
dwtools3.egg-info/dependency_links.txt
dwtools3.egg-info/top_level.txt
dwtools3/_docs/Makefile
dwtools3/_docs/make.bat
dwtools3/_docs/source/conf.py
dwtools3/_docs/source/index.rst
dwtools3/_docs/source/_static/.gitignore
dwtools3/_docs/source/_templates/.gitignore
dwtools3/_docs/source/packages/datatypes.rst
dwtools3/_docs/source/packages/django.rst
dwtools3/_docs/source/packages/excel.rst
dwtools3/_docs/source/packages/http.rst
dwtools3/_docs/source/packages/io.rst
dwtools3/_docs/source/packages/report_writer.rst
dwtools3/_docs/source/packages/system.rst
dwtools3/_docs/source/packages/datatypes/enum.rst
dwtools3/_docs/source/packages/django/authx.rst
dwtools3/_docs/source/packages/django/duration.rst
dwtools3/_docs/source/packages/django/email.rst
dwtools3/_docs/source/packages/django/helpers.rst
dwtools3/_docs/source/packages/django/salesforce.rst
dwtools3/_docs/source/packages/django/seo.rst
dwtools3/_docs/source/packages/http/urlparser.rst
dwtools3/_docs/source/packages/http/utils.rst
dwtools3/_docs/source/packages/io/utils.rst
dwtools3/_docs/source/packages/system/lockfile.rst
dwtools3/_docs/source/packages/system/tempfile.rst
dwtools3/datatypes/__init__.py
dwtools3/datatypes/dates.py
dwtools3/datatypes/enumx.py
dwtools3/django/__init__.py
dwtools3/django/authx/__init__.py
dwtools3/django/authx/admin.py
dwtools3/django/authx/api.py
dwtools3/django/authx/models.py
dwtools3/django/authx/settings.py
dwtools3/django/authx/validators.py
dwtools3/django/duration/__init__.py
dwtools3/django/duration/forms.py
dwtools3/django/duration/utils.py
dwtools3/django/duration/widgets.py
dwtools3/django/email/__init__.py
dwtools3/django/email/backends.py
dwtools3/django/email/messages.py
dwtools3/django/email/settings.py
dwtools3/django/email/templates.py
dwtools3/django/email/boilerplate/README.markdown
dwtools3/django/email/boilerplate/email.html
dwtools3/django/email/boilerplate/email_lite.html
dwtools3/django/helpers/__init__.py
dwtools3/django/helpers/admin.py
